{
  "wine-batches": [
    {
      "id": "b123e456-78d9-42a3-b456-426614174000",
      "internalCode": "B2025-VINEYARD01",
      "receptionDate": "14/03/2025",
      "harvestCampaign": "2025",
      "vineyardOrigin": "Valle de Ica",
      "grapeVariety": "Malbec",
      "initialGrapeQuantityKg": 1500,
      "createdBy": "juan.perez@elixirline.com",
      "status": "InProcess",
      "currentStage": "Fermentation"
    },
    {
      "id": "a223c789-11af-47c2-8bf7-227399911000",
      "internalCode": "B2025-VINEYARD02",
      "receptionDate": "17/03/2025",
      "harvestCampaign": "2025",
      "vineyardOrigin": "Valle del Colca",
      "grapeVariety": "Cabernet Sauvignon",
      "initialGrapeQuantityKg": 2000,
      "createdBy": "maria.lopez@elixirline.com",
      "status": "Completed",
      "currentStage": "Aging"
    },
    {
      "id": "c323f111-9abf-4d21-91a1-132145889000",
      "internalCode": "B2024-VINEYARD03",
      "receptionDate": "20/04/2024",
      "harvestCampaign": "2024",
      "vineyardOrigin": "Cañete",
      "grapeVariety": "Syrah",
      "initialGrapeQuantityKg": 1200,
      "createdBy": "carlos.fernandez@elixirline.com",
      "status": "InProcess",
      "currentStage": "Clarification"
    },
    {
      "id": "d423e222-56cd-4d43-bb3e-556700008000",
      "internalCode": "B2023-VINEYARD04",
      "receptionDate": "10/05/2023",
      "harvestCampaign": "2023",
      "vineyardOrigin": "Moquegua",
      "grapeVariety": "Tannat",
      "initialGrapeQuantityKg": 1800,
      "createdBy": "ana.silva@elixirline.com",
      "status": "Archived",
      "currentStage": "Completed"
    },
    {
      "id": "e523a333-8ef5-4012-9873-661211119000",
      "internalCode": "B2025-VINEYARD05",
      "receptionDate": "20/03/2025",
      "harvestCampaign": "2025",
      "vineyardOrigin": "Arequipa",
      "grapeVariety": "Tempranillo",
      "initialGrapeQuantityKg": 1700,
      "createdBy": "luis.rios@elixirline.com",
      "status": "InProcess",
      "currentStage": "Pressing"
    }
  ],
  "campaigns": [
    {
      "id": "cmp-2025-001",
      "name": "Vendimia 2025",
      "startDate": "01/03/2025",
      "createdBy": "Gonzalo Saldaña",
      "endDate": "30/05/2025",
      "batchesQuantity": "5",
      "status": "InProcess"
    },
    {
      "id": "cmp-2024-002",
      "name": "Vendimia 2024",
      "createdBy": "carlos.mendoza@elixirline.com",
      "startDate": "10/02/2024",
      "endDate": "25/04/2024",
      "batchesQuantity": 9,
      "status": "Completed"
    },
    {
      "id": "cmp-2023-003",
      "name": "Vendimia Experimental",
      "createdBy": "sofia.gomez@elixirline.com",
      "startDate": "05/01/2023",
      "endDate": "28/02/2023",
      "batchesQuantity": 5,
      "status": "Archived"
    },
    {
      "id": "cmp-2025-004",
      "name": "Selección Premium 2025",
      "createdBy": "juan.vera@elixirline.com",
      "startDate": "15/03/2025",
      "endDate": "20/05/2025",
      "batchesQuantity": 7,
      "status": "InProcess"
    },
    {
      "id": "cmp-2022-005",
      "name": "Microvinificación 2022",
      "createdBy": "mariana.luna@elixirline.com",
      "startDate": "01/02/2022",
      "endDate": "15/03/2022",
      "batchesQuantity": 3,
      "status": "Archived"
    }
  ],
  "supplies": [
    {
      "id": "sup-001",
      "name": "Metabisulfito de Potasio",
      "quantity": "30",
      "unidad": "kg",
      "image": "https://w7.pngwing.com/pngs/218/434/png-transparent-computer-icons-box-cargo-packaging-and-labeling-box-miscellaneous-service-logo.png"
    },
    {
      "id": "sup-002",
      "name": "Ácido Tartárico",
      "quantity": 10,
      "unidad": "kg",
      "image": "https://w7.pngwing.com/pngs/218/434/png-transparent-computer-icons-box-cargo-packaging-and-labeling-box-miscellaneous-service-logo.png"
    },
    {
      "id": "sup-003",
      "name": "Bentonita",
      "quantity": 15,
      "unidad": "kg",
      "image": "https://w7.pngwing.com/pngs/218/434/png-transparent-computer-icons-box-cargo-packaging-and-labeling-box-miscellaneous-service-logo.png"
    },
    {
      "id": "sup-004",
      "name": "Contenedor de Acero Inoxidable 500L",
      "quantity": 4,
      "unidad": "units",
      "image": "https://w7.pngwing.com/pngs/218/434/png-transparent-computer-icons-box-cargo-packaging-and-labeling-box-miscellaneous-service-logo.png"
    },
    {
      "id": "sup-005",
      "name": "Desinfectante Enológico",
      "quantity": 20,
      "unidad": "L",
      "image": "https://w7.pngwing.com/pngs/218/434/png-transparent-computer-icons-box-cargo-packaging-and-labeling-box-miscellaneous-service-logo.png"
    },
    {
      "id": "sup-001",
      "name": "Metabisulfito de Potasio",
      "quantity": 25,
      "unidad": "kg",
      "image": "https://w7.pngwing.com/pngs/218/434/png-transparent-computer-icons-box-cargo-packaging-and-labeling-box-miscellaneous-service-logo.png"
    },
    {
      "id": "sup-002",
      "name": "Ácido Tartárico",
      "quantity": 10,
      "unidad": "kg",
      "image": "https://w7.pngwing.com/pngs/218/434/png-transparent-computer-icons-box-cargo-packaging-and-labeling-box-miscellaneous-service-logo.png"
    },
    {
      "id": "sup-003",
      "name": "Bentonita",
      "quantity": 15,
      "unidad": "kg",
      "image": "https://w7.pngwing.com/pngs/218/434/png-transparent-computer-icons-box-cargo-packaging-and-labeling-box-miscellaneous-service-logo.png"
    },
    {
      "id": "sup-004",
      "name": "Contenedor de Acero Inoxidable 500L",
      "quantity": 4,
      "unidad": "units",
      "image": "https://w7.pngwing.com/pngs/218/434/png-transparent-computer-icons-box-cargo-packaging-and-labeling-box-miscellaneous-service-logo.png"
    },
    {
      "id": "sup-005",
      "name": "Desinfectante Enológico",
      "quantity": 20,
      "unidad": "L",
      "image": "https://w7.pngwing.com/pngs/218/434/png-transparent-computer-icons-box-cargo-packaging-and-labeling-box-miscellaneous-service-logo.png"
    }
  ],
  "employees": [
    {
      "id": "u001",
      "firstName": "Maria",
      "lastName": "Silva",
      "email": "ana.silva@elixirline.com",
      "phoneNumber": "+51 987654321",
      "password": "Ana@2025"
    },
    {
      "id": "u002",
      "firstName": "Carlos",
      "lastName": "Mendoza",
      "email": "carlos.mendoza@elixirline.com",
      "phoneNumber": "+51 956782341",
      "password": "Carlos#2024"
    },
    {
      "id": "u003",
      "firstName": "Sofía",
      "lastName": "Gómez",
      "email": "sofia.gomez@elixirline.com",
      "phoneNumber": "+51 912345678",
      "password": "Sofia2023!"
    },
    {
      "id": "u004",
      "firstName": "Juan",
      "lastName": "Vera",
      "email": "juan.vera@elixirline.com",
      "phoneNumber": "+51 934567890",
      "password": "Jv!123456"
    },
    {
      "id": "u005",
      "firstName": "Mariana",
      "lastName": "Luna",
      "email": "mariana.luna@elixirline.com",
      "phoneNumber": "+51 923456789",
      "password": "Mari@1234"
    },
    {
      "id": "u006",
      "firstName": "Ana",
      "lastName": "Silva",
      "email": "ana.silva@elixirline.com",
      "phoneNumber": "+51 987654321",
      "password": "Ana@2025"
    },
    {
      "id": "u007",
      "firstName": "Carlos",
      "lastName": "Mendoza",
      "email": "carlos.mendoza@elixirline.com",
      "phoneNumber": "+51 956782341",
      "password": "Carlos#2024"
    },
    {
      "id": "u008",
      "firstName": "Sofía",
      "lastName": "Gómez",
      "email": "sofia.gomez@elixirline.com",
      "phoneNumber": "+51 912345678",
      "password": "Sofia2023!"
    },
    {
      "id": "u009",
      "firstName": "Juan",
      "lastName": "Vera",
      "email": "juan.vera@elixirline.com",
      "phoneNumber": "+51 934567890",
      "password": "Jv!123456"
    },
    {
      "id": "u010",
      "firstName": "Mariana",
      "lastName": "Luna",
      "email": "mariana.luna@elixirline.com",
      "phoneNumber": "+51 923456789",
      "password": "Mari@1234"
    }
  ],
  "users": [
    {
      "id": "USR-001",
      "email": "luisprada@gmail.com",
      "password": "securePass01",
      "role": "admin"
    },
    {
      "id": "USR-002",
      "email": "mfsalazar@gmail.com",
      "password": "securePass02",
      "role": "admin"
    },
    {
      "id": "USR-003",
      "email": "jorgeparedes@outlook.com",
      "password": "securePass03",
      "role": "admin"
    },
    {
      "id": "USR-004",
      "email": "lucia.nt@gmail.com",
      "password": "securePass04",
      "role": "admin"
    },
    {
      "id": "USR-005",
      "email": "rgomez@hotmail.com",
      "password": "securePass05",
      "role": "admin"
    },
    {
      "id": "USR-006",
      "email": "valenriosi@gmail.com",
      "password": "securePass06",
      "role": "admin"
    },
    {
      "id": "USR-007",
      "email": "cerv_ramirez@gmail.com",
      "password": "securePass07",
      "role": "admin"
    },
    {
      "id": "USR-008",
      "email": "ana.mendoza@correo.com",
      "password": "securePass08",
      "role": "admin"
    },
    {
      "id": "USR-009",
      "email": "g.sotoq@gmail.com",
      "password": "securePass09",
      "role": "admin"
    },
    {
      "id": "USR-010",
      "email": "isabelacd@correo.pe",
      "password": "securePass10",
      "role": "admin"
    }
  ],
  "profiles": [
    {
      "id": "1",
      "user_id": "USR-001",
      "name": "Luis Carlos",
      "surname": "Prada Naez",
      "email": "luisprada@gmail.com",
      "country": "Peru",
      "phone": "+51 903 456 781",
      "user_type": "Winemaker"
    },
    {
      "id": "2",
      "user_id": "USR-002",
      "name": "María Fernanda",
      "surname": "Salazar Ruiz",
      "email": "mfsalazar@gmail.com",
      "country": "Chile",
      "phone": "+56 912 334 889",
      "user_type": "Enologist"
    },
    {
      "id": "3",
      "user_id": "USR-003",
      "name": "Jorge Andrés",
      "surname": "Paredes León",
      "email": "jorgeparedes@outlook.com",
      "country": "Argentina",
      "phone": "+54 911 2345 6789",
      "user_type": "Winemaker"
    },
    {
      "id": "4",
      "user_id": "USR-004",
      "name": "Lucía",
      "surname": "Navarro Torres",
      "email": "lucia.nt@gmail.com",
      "country": "Mexico",
      "phone": "+52 553 001 2233",
      "user_type": "Field Technician"
    },
    {
      "id": "5",
      "user_id": "USR-005",
      "name": "Ricardo",
      "surname": "Gómez Yupanqui",
      "email": "rgomez@hotmail.com",
      "country": "Peru",
      "phone": "+51 988 234 112",
      "user_type": "Winemaker"
    },
    {
      "id": "6",
      "user_id": "USR-006",
      "name": "Valentina",
      "surname": "Ríos Ibáñez",
      "email": "valenriosi@gmail.com",
      "country": "Chile",
      "phone": "+56 987 123 456",
      "user_type": "Agronomist"
    },
    {
      "id": "7",
      "user_id": "USR-007",
      "name": "Carlos Eduardo",
      "surname": "Ramírez Vega",
      "email": "cerv_ramirez@gmail.com",
      "country": "Colombia",
      "phone": "+57 300 456 7890",
      "user_type": "Winemaker"
    },
    {
      "id": "8",
      "user_id": "USR-008",
      "name": "Ana Sofía",
      "surname": "Mendoza López",
      "email": "ana.mendoza@correo.com",
      "country": "Ecuador",
      "phone": "+593 99 456 7891",
      "user_type": "Enologist"
    },
    {
      "id": "9",
      "user_id": "USR-009",
      "name": "Gabriel",
      "surname": "Soto Quispe",
      "email": "g.sotoq@gmail.com",
      "country": "Peru",
      "phone": "+51 912 876 345",
      "user_type": "Field Technician"
    },
    {
      "id": "10",
      "user_id": "USR-010",
      "name": "Isabela",
      "surname": "Castro Durand",
      "email": "isabelacd@correo.pe",
      "country": "Peru",
      "phone": "+51 984 112 768",
      "user_type": "Winemaker"
    },
    {
      "id": "",
      "user_id": "",
      "name": "",
      "surname": "",
      "email": "",
      "country": "",
      "phone": "",
      "user_type": ""
    }
  ],
  "tasks": [
    {
      "id": "e003",
      "relatedId": "B2025-VINEYARD01",
      "assignee": "Sofía Gómez",
      "title": "Tarea Vineyard 1",
      "startDate": "2025-06-10T05:00:00.000Z",
      "dueDate": "2025-06-26T05:00:00.000Z",
      "type": "CAMPO",
      "status": "InProcess",
      "progress": 0,
      "description": "Lorem ipsos",
      "supplies": [
        {
          "id": "sup-002",
          "quantity": 1
        }
      ]
    },
    {
      "id": "e004",
      "relatedId": "B2025-VINEYARD02",
      "assignee": "Carlos Mendoza",
      "title": "Control de temperatura",
      "startDate": "2025-06-15T08:00:00.000Z",
      "dueDate": "2025-06-20T17:00:00.000Z",
      "type": "INDUSTRIAL",
      "status": "InProcess",
      "progress": 0,
      "description": "Verificar y registrar temperatura de los tanques.",
      "supplies": [
        {
          "id": "sup-001",
          "quantity": 2
        }
      ]
    },
    {
      "id": "e005",
      "relatedId": "B2024-VINEYARD03",
      "assignee": "Sofía Gómez",
      "title": "Control de pH",
      "startDate": "2025-06-19T09:00:00.000Z",
      "dueDate": "2025-06-19T11:00:00.000Z",
      "type": "CAMPO",
      "status": "InProcess",
      "progress": 0,
      "description": "Medir y registrar el pH de los mostos en fermentación.",
      "supplies": [
        {
          "id": "sup-002",
          "quantity": 1
        }
      ]
    },
    {
      "id": "e006",
      "relatedId": "B2025-VINEYARD05",
      "assignee": "Mariana Luna",
      "title": "Revisión de clarificación",
      "startDate": "2025-06-20T10:00:00.000Z",
      "dueDate": "2025-06-21T16:00:00.000Z",
      "type": "INDUSTRIAL",
      "status": "Completed",
      "progress": 0,
      "description": "Verificar el proceso de clarificación y registrar observaciones.",
      "supplies": [
        {
          "id": "sup-003",
          "quantity": 2
        }
      ]
    },
    {
      "id": "23ab",
      "assignee": "Ana Silva",
      "title": "Tarea de Irrigación",
      "startDate": "2025-08-12",
      "dueDate": "2025-08-20",
      "type": "CAMPO",
      "status": "Pending",
      "progress": 0,
      "description": "Descripcion 1",
      "supplies": [
        {
          "id": "sup-002",
          "quantity": 2
        },
        {
          "id": "sup-005",
          "quantity": 1
        }
      ],
      "suppliesIds": [],
      "relatedId": "B2025-VINEYARD01"
    }
  ],
  "evidences": [
    {
      "id": "1750391561913",
      "taskId": "e003",
      "percentage": 70,
      "description": "Evidencia 1",
      "image": "https://www.shutterstock.com/image-photo/wide-open-field-stretching-towards-600nw-2476599713.jpg",
      "createdAt": "2025-06-19T12:52:41.913Z",
      "type": "CAMPO"
    },
    {
      "id": "1750391561914",
      "taskId": "e004",
      "percentage": 60,
      "description": "Registro de temperatura completado.",
      "image": "https://www.shutterstock.com/image-photo/wide-open-field-stretching-towards-600nw-2476599713.jpg",
      "createdAt": "2025-06-16T18:00:00.000Z",
      "type": "INDUSTRIAL"
    },
    {
      "id": "1750391561914",
      "taskId": "e004",
      "percentage": 70,
      "description": "Registro de temperatura completado.",
      "image": "https://static.vecteezy.com/system/resources/previews/006/240/309/non_2x/nature-scenic-trees-and-green-meadow-field-rural-landscape-with-bright-cloudy-blue-sky-idyllic-adventure-landscape-natural-colorful-foliage-photo.jpg",
      "createdAt": "2025-06-16T19:00:00.000Z",
      "type": "INDUSTRIAL"
    },
    {
      "id": "1750391561915",
      "taskId": "e005",
      "percentage": 80,
      "description": "Medición de pH realizada en todos los tanques.",
      "image": "https://www.shutterstock.com/image-photo/wide-open-field-stretching-towards-600nw-2476599713.jpg",
      "createdAt": "2025-06-19T12:00:00.000Z",
      "type": "CAMPO"
    },
    {
      "id": "1750391561916",
      "taskId": "e006",
      "percentage": 100,
      "description": "Clarificación verificada y documentada.",
      "image": "https://www.shutterstock.com/image-photo/wide-open-field-stretching-towards-600nw-2476599713.jpg",
      "createdAt": "2025-06-17T17:00:00.000Z",
      "type": "INDUSTRIAL"
    }
  ],
  "incidences": [
    {
      "id": "a4f3",
      "taskId": "e006",
      "description": "Esta perfecto",
      "image": "https://www.gastronomiaycia.com/wp-content/uploads/2017/08/ava_winery_1-680x451.jpg",
      "createdAt": "2025-06-19T14:33:16.136Z",
      "type": "INDUSTRIAL"
    },
    {
      "id": "a4f4",
      "taskId": "e005",
      "description": "Incidencia de campo",
      "image": "https://sp-ao.shortpixel.ai/client/to_auto,q_glossy,ret_img,w_4999,h_3332/https://cii.conchaytoro.com/web/wp-content/uploads/2015/05/noticia3.jpg",
      "createdAt": "2025-06-17T17:33:16.136Z",
      "type": "CAMPO"
    }
  ],
  "map": [
    {
      "id": "b0e3",
      "type": "polygon",
      "path": [
        {
          "lat": -9.054917703658194,
          "lng": -78.53762681557836
        },
        {
          "lat": -9.057765669742086,
          "lng": -78.54078538386656
        },
        {
          "lat": -9.060884834943254,
          "lng": -78.53776414782314
        }
      ],
      "label": "Lote - 1 - Chimbote",
      "wineBatchId": "d423e222-56cd-4d43-bb3e-556700008000"
    },
    {
      "id": "15ff",
      "type": "polygon",
      "path": [
        {
          "lat": -9.054381146948387,
          "lng": -78.53766232022797
        },
        {
          "lat": -9.057305396049426,
          "lng": -78.54096680173431
        },
        {
          "lat": -9.055101616326526,
          "lng": -78.54315548429047
        },
        {
          "lat": -9.054084482667163,
          "lng": -78.54002266416107
        }
      ],
      "label": "Lote - 2 - Chimbote",
      "wineBatchId": "b123e456-78d9-42a3-b456-426614174000"
    }
  ]
}